tap_zuora/__init__.py
tap_zuora/apis.py
tap_zuora/client.py
tap_zuora/discover.py
tap_zuora/sync.py
pipelinewise_tap_zuora-1.0.0.dist-info/LICENSE
pipelinewise_tap_zuora-1.0.0.dist-info/METADATA
pipelinewise_tap_zuora-1.0.0.dist-info/WHEEL
pipelinewise_tap_zuora-1.0.0.dist-info/entry_points.txt
pipelinewise_tap_zuora-1.0.0.dist-info/top_level.txt
pipelinewise_tap_zuora-1.0.0.dist-info/RECORD
