Metadata-Version: 2.1
Name: pipelinewise-tap-zuora
Version: 1.0.0
Summary: Singer.io tap for extracting data from the Zuora API - PipelineWise compatible
Home-page: https://github.com/transferwise/pipelinewise-tap-zuora
Author: Stitch
License: UNKNOWN
Platform: UNKNOWN
Classifier: License :: OSI Approved :: GNU Affero General Public License v3
Classifier: Programming Language :: Python :: 3 :: Only
Requires-Dist: pipelinewise-singer-python (==1.*)
Requires-Dist: requests (==2.20.0)
Requires-Dist: pendulum (==1.2.0)
Provides-Extra: test
Requires-Dist: ipdb ; extra == 'test'
Requires-Dist: pylint ; extra == 'test'
